ipset_c/__init__.py
ipset_c/__init__.pyi
ipset_c_ext.cp313-win_amd64.pyd
ipset_c-0.1.1.dist-info/LICENSE
ipset_c-0.1.1.dist-info/METADATA
ipset_c-0.1.1.dist-info/WHEEL
ipset_c-0.1.1.dist-info/RECORD
